duodata/__init__.py
duodata/__main__.py
duodata/algemeen.py
duodata/cli.py
duodata/settings.py
duodata/hbo/__init__.py
duodata/hbo/toestroom.py
duodata/mbo/__init__.py
duodata/mbo/gediplomeerden.py
duodata/vo/__init__.py
duodata/vo/examenkandidaten.py
duodata/vo/leerlingen.py
duodata/vo/prognoses.py
duodata-0.2.1.dist-info/AUTHORS.rst
duodata-0.2.1.dist-info/LICENSE
duodata-0.2.1.dist-info/METADATA
duodata-0.2.1.dist-info/WHEEL
duodata-0.2.1.dist-info/entry_points.txt
duodata-0.2.1.dist-info/top_level.txt
duodata-0.2.1.dist-info/RECORD
