Metadata-Version: 2.1
Name: duodata
Version: 0.2.1
Summary: A package that extracts data from Dienst Uitvoering Onderwijs (DUO).
Home-page: https://github.com/enningb/python-duo
Author: Bram Enning
Author-email: bramenning@gmail.com
License: MIT license
Platform: UNKNOWN
Classifier: Development Status :: 5 - Production/Stable
Classifier: Intended Audience :: Developers
Classifier: License :: OSI Approved :: MIT License
Classifier: Operating System :: Unix
Classifier: Operating System :: POSIX
Classifier: Operating System :: Microsoft :: Windows
Classifier: Programming Language :: Python
Classifier: Topic :: Utilities
Requires-Dist: pandas
Requires-Dist: numpy
